parsestudio/__init__.py
parsestudio/parse.py
parsestudio/parsers/__init__.py
parsestudio/parsers/docling_parser.py
parsestudio/parsers/llama_parser.py
parsestudio/parsers/pymupdf_parser.py
parsestudio/parsers/schemas.py
parsestudio-1.0.4.dist-info/METADATA
parsestudio-1.0.4.dist-info/WHEEL
parsestudio-1.0.4.dist-info/top_level.txt
parsestudio-1.0.4.dist-info/RECORD
