Metadata-Version: 2.1
Name: parsestudio
Version: 1.0.4
Summary: Parse PDF files using different parsers.
Author: Imene KOLLI
Author-email: imene.kolli@df.uzh.ch
Requires-Python: >=3.12,<3.13
Requires-Dist: docling<3.0.0,>=2.5.2
Requires-Dist: pymupdf<2.0.0,>=1.24.13
Requires-Dist: llama-parse<0.6.0,>=0.5.14
Requires-Dist: pytest<9.0.0,>=8.3.3
Requires-Dist: python-dotenv<2.0.0,>=1.0.1
